LICENSE
README.md
setup.py
trenasty/__init__.py
trenasty.egg-info/PKG-INFO
trenasty.egg-info/SOURCES.txt
trenasty.egg-info/dependency_links.txt
trenasty.egg-info/not-zip-safe
trenasty.egg-info/requires.txt
trenasty.egg-info/top_level.txt
trenasty/configs/__init__.py
trenasty/configs/config.py
trenasty/middleware/__init__.py
trenasty/middleware/treblle.py
trenasty/utils/__init__.py
trenasty/utils/data_build.py
trenasty/utils/helper.py