Metadata-Version: 2.1
Name: trenasty
Version: 1.0.2
Summary: Treblle Python-FastAPI SDK
Home-page: UNKNOWN
Author: Dev-Dynasty
Author-email: mcdonaldamure@gmail.com
License: MIT
Keywords: treblle python fastapi sdk api logging monitoring error-tracking performance
Platform: UNKNOWN
License-File: LICENSE
